byted_sophon_atum_test/__init__.py
byted_sophon_atum_test-0.0.1.dist-info/METADATA
byted_sophon_atum_test-0.0.1.dist-info/WHEEL
byted_sophon_atum_test-0.0.1.dist-info/top_level.txt
byted_sophon_atum_test-0.0.1.dist-info/RECORD
